momentpy/__init__.py
momentpy/moment.py
momentpy-0.1.3.dist-info/licenses/LICENSE
momentpy-0.1.3.dist-info/METADATA
momentpy-0.1.3.dist-info/WHEEL
momentpy-0.1.3.dist-info/top_level.txt
momentpy-0.1.3.dist-info/RECORD
