Metadata-Version: 2.4
Name: momentpy
Version: 0.1.3
Summary: A Carbon-like datetime library for Python inspired by Laravel's Carbon
Author-email: Sandesh Satyal <sandeshsatyal@gmail.com>
License-Expression: MIT
Project-URL: Homepage, https://github.com/sandysh/pycarbon
Requires-Python: >=3.8
License-File: LICENSE
Dynamic: license-file
